README.md
setup.py
disnake/ext/loader/__init__.py
disnake/ext/loader/loader.py
disnake_cog_loader.egg-info/PKG-INFO
disnake_cog_loader.egg-info/SOURCES.txt
disnake_cog_loader.egg-info/dependency_links.txt
disnake_cog_loader.egg-info/requires.txt
disnake_cog_loader.egg-info/top_level.txt