Metadata-Version: 2.1
Name: disnake-cog-loader
Version: 0.0.1
Summary: An extension module for disnake to load cogs without needing the setup function.
Home-page: https://github.com/m-y-x-i/disnake-cog-loader
Author: Myxi
License: UNKNOWN
Platform: UNKNOWN
Requires-Python: >=3.8.0
